athina/__init__.py
athina/cli/__init__.py
athina/cli/cli.py
athina/constants/__init__.py
athina/constants/messages.py
athina/datasets/__init__.py
athina/datasets/conversations.json
athina/datasets/dataset.py
athina/datasets/summarization_sample.py
athina/datasets/yc_query_mini.py
athina/errors/__init__.py
athina/errors/exceptions.py
athina/evals/__init__.py
athina/evals/base_evaluator.py
athina/evals/conversation/conversation_coherence/evaluator.py
athina/evals/conversation/conversation_coherence/prompt.py
athina/evals/conversation/conversation_resolution/evaluator.py
athina/evals/conversation/conversation_resolution/prompt.py
athina/evals/eval_type.py
athina/evals/function/__init__.py
athina/evals/function/function_evaluator.py
athina/evals/function/functions.py
athina/evals/function/wrapper.py
athina/evals/grounded/__init__.py
athina/evals/grounded/grounded_evaluator.py
athina/evals/grounded/similarity.py
athina/evals/grounded/wrapper.py
athina/evals/guardrails/correct_language/evaluator.py
athina/evals/guardrails/detect_pii/evaluator.py
athina/evals/guardrails/gibberish_text/evaluator.py
athina/evals/guardrails/no_secrets_present/evaluator.py
athina/evals/guardrails/politeness_check/evaluator.py
athina/evals/guardrails/profanity_free/evaluator.py
athina/evals/guardrails/reading_time/evaluator.py
athina/evals/guardrails/restrict_to_topic/evaluator.py
athina/evals/guardrails/sensitive_topics/evaluator.py
athina/evals/guardrails/sfw/evaluator.py
athina/evals/guardrails/toxic_language/evaluator.py
athina/evals/guardrails/unusual_prompt/evaluator.py
athina/evals/llm/__init__.py
athina/evals/llm/context_contains_enough_information/__init__.py
athina/evals/llm/context_contains_enough_information/evaluator.py
athina/evals/llm/context_contains_enough_information/examples.py
athina/evals/llm/custom_prompt/__init__.py
athina/evals/llm/custom_prompt/evaluator.py
athina/evals/llm/does_response_answer_query/__init__.py
athina/evals/llm/does_response_answer_query/evaluator.py
athina-1.7.39.dist-info/METADATA
athina-1.7.39.dist-info/WHEEL
athina-1.7.39.dist-info/entry_points.txt
athina-1.7.39.dist-info/RECORD
